{"nodes": [{"id": 562769058, "lat": 49.6653248, "lon": 21.823906, "way_id": 233604538, "landuse": "farmland", "closest_distance_restriction": 1.9519795545972651}, {"id": 1821215125, "lat": 49.6532688, "lon": 21.8243938, "way_id": 233604538, "landuse": "farmland", "closest_distance_restriction": 2.8437363642862516}, {"id": 2043655062, "lat": 49.6583083, "lon": 21.8277416, "way_id": 233604538, "landuse": "farmland", "closest_distance_restriction": 2.6308332226275457}, {"id": 2043655065, "lat": 49.6629197, "lon": 21.8222913, "way_id": 233604538, "landuse": "farmland", "closest_distance_restriction": 2.0020448285652512}, {"id": 2043655071, "lat": 49.664385, "lon": 21.8200844, "way_id": 233604538, "landuse": "farmland", "closest_distance_restriction": 1.777132381483961}, {"id": 2043655077, "lat": 49.6577874, "lon": 21.8290719, "way_id": 233604538, "landuse": "farmland", "closest_distance_restriction": 2.7411121058256955}, {"id": 2043655085, "lat": 49.6629058, "lon": 21.8222049, "way_id": 233604538, "landuse": "farmland", "closest_distance_restriction": 1.9980596460582971}, {"id": 2043655100, "lat": 49.6536455, "lon": 21.8160396, "way_id": 233604538, "landuse": "farmland", "closest_distance_restriction": 2.2626944387295764}, {"id": 2043655112, "lat": 49.6564747, "lon": 21.8285784, "way_id": 233604538, "landuse": "farmland", "closest_distance_restriction": 2.8127075258308007}, {"id": 2043655141, "lat": 49.6646277, "lon": 21.816766, "way_id": 233604538, "landuse": "farmland", "closest_distance_restriction": 1.5736125957389424}, {"id": 2043655151, "lat": 49.6653761, "lon": 21.8228289, "way_id": 233604538, "landuse": "farmland", "closest_distance_restriction": 1.8818030660327456}, {"id": 2043655161, "lat": 49.6655305, "lon": 21.8185255, "way_id": 233604538, "landuse": "farmland", "closest_distance_restriction": 1.6115976955590505}, {"id": 2043655163, "lat": 49.6654509, "lon": 21.8234546, "way_id": 233604538, "landuse": "farmland", "closest_distance_restriction": 1.9167819211423367}, {"id": 2043655191, "lat": 49.6560302, "lon": 21.8285248, "way_id": 233604538, "landuse": "farmland", "closest_distance_restriction": 2.8441885012675594}, {"id": 2043655197, "lat": 49.6645444, "lon": 21.8183538, "way_id": 233604538, "landuse": "farmland", "closest_distance_restriction": 1.6674972683197173}, {"id": 2043655228, "lat": 49.6648055, "lon": 21.8218764, "way_id": 233604538, "landuse": "farmland", "closest_distance_restriction": 1.8565875702604497}, {"id": 2043655230, "lat": 49.6579957, "lon": 21.8290719, "way_id": 233604538, "landuse": "farmland", "closest_distance_restriction": 2.7260434365497086}, {"id": 2043655255, "lat": 49.6613363, "lon": 21.8226454, "way_id": 233604538, "landuse": "farmland", "closest_distance_restriction": 2.1330916011238332}, {"id": 2043655277, "lat": 49.6585236, "lon": 21.8284282, "way_id": 233604538, "landuse": "farmland", "closest_distance_restriction": 2.6527538778426463}, {"id": 2043655281, "lat": 49.6591209, "lon": 21.8278231, "way_id": 233604538, "landuse": "farmland", "closest_distance_restriction": 2.576764066991307}, {"id": 2043655287, "lat": 49.6586069, "lon": 21.8277952, "way_id": 233604538, "landuse": "farmland", "closest_distance_restriction": 2.612023004687422}, {"id": 2043655312, "lat": 49.6587111, "lon": 21.8282673, "way_id": 233604538, "landuse": "farmland", "closest_distance_restriction": 2.630481581181822}, {"id": 2043655320, "lat": 49.6615308, "lon": 21.8229779, "way_id": 233604538, "landuse": "farmland", "closest_distance_restriction": 2.137288192794708}, {"id": 2043655334, "lat": 49.6570025, "lon": 21.8286642, "way_id": 233604538, "landuse": "farmland", "closest_distance_restriction": 2.7771882368909537}, {"id": 2043655337, "lat": 49.6575693, "lon": 21.8091044, "way_id": 233604538, "landuse": "farmland", "closest_distance_restriction": 1.6541411818525573}, {"id": 2043655406, "lat": 49.6650771, "lon": 21.8221086, "way_id": 233604538, "landuse": "farmland", "closest_distance_restriction": 1.8545127400068466}, {"id": 2043655427, "lat": 49.664378, "lon": 21.8187787, "way_id": 233604538, "landuse": "farmland", "closest_distance_restriction": 1.7029533617244104}, {"id": 2043655429, "lat": 49.6573637, "lon": 21.8282243, "way_id": 233604538, "landuse": "farmland", "closest_distance_restriction": 2.726716203275238}, {"id": 2043655435, "lat": 49.6620933, "lon": 21.8223664, "way_id": 233604538, "landuse": "farmland", "closest_distance_restriction": 2.0634636024362516}, {"id": 2043655443, "lat": 49.6558552, "lon": 21.8122459, "way_id": 233604538, "landuse": "farmland", "closest_distance_restriction": 1.9232148890821346}, {"id": 2043655559, "lat": 49.6620933, "lon": 21.8229028, "way_id": 233604538, "landuse": "farmland", "closest_distance_restriction": 2.093420955854732}, {"id": 2334627712, "lat": 49.6517166, "lon": 21.8212166, "way_id": 233604538, "landuse": "farmland", "closest_distance_restriction": 2.6886730475103735}, {"id": 3183780292, "lat": 49.6510374, "lon": 21.8198453, "way_id": 233604538, "landuse": "farmland", "closest_distance_restriction": 2.629010645517739}, {"id": 3183780293, "lat": 49.6511611, "lon": 21.8200898, "way_id": 233604538, "landuse": "farmland", "closest_distance_restriction": 2.6391979957897256}, {"id": 3186982209, "lat": 49.6542317, "lon": 21.8151955, "way_id": 233604538, "landuse": "farmland", "closest_distance_restriction": 2.1827009979586878}, {"id": 3186982212, "lat": 49.6548547, "lon": 21.8140976, "way_id": 233604538, "landuse": "farmland", "closest_distance_restriction": 2.084845751291206}, {"id": 3265936164, "lat": 49.6596179, "lon": 21.8288467, "way_id": 233604538, "landuse": "farmland", "closest_distance_restriction": 2.5998861049980464}, {"id": 3265936167, "lat": 49.6613551, "lon": 21.8276919, "way_id": 233604538, "landuse": "farmland", "closest_distance_restriction": 2.4183297943125135}, {"id": 3265936169, "lat": 49.6617246, "lon": 21.826996, "way_id": 233604538, "landuse": "farmland", "closest_distance_restriction": 2.3537231654678417}, {"id": 3265936170, "lat": 49.6619434, "lon": 21.8267802, "way_id": 233604538, "landuse": "farmland", "closest_distance_restriction": 2.3270588973090707}, {"id": 3265936172, "lat": 49.6620933, "lon": 21.8228538, "way_id": 233604538, "landuse": "farmland", "closest_distance_restriction": 2.090672592423704}, {"id": 3265936173, "lat": 49.6628603, "lon": 21.8203221, "way_id": 233604538, "landuse": "farmland", "closest_distance_restriction": 1.8958535711130828}, {"id": 3265936174, "lat": 49.6634208, "lon": 21.8255449, "way_id": 233604538, "landuse": "farmland", "closest_distance_restriction": 2.1619460140001077}, {"id": 3265936183, "lat": 49.6654523, "lon": 21.823162, "way_id": 233604538, "landuse": "farmland", "closest_distance_restriction": 1.8983663090387195}, {"id": 7726919303, "lat": 49.6529307, "lon": 21.8237348, "way_id": 233604538, "landuse": "farmland", "closest_distance_restriction": 2.8104544052419027}, {"id": 7726919304, "lat": 49.652335, "lon": 21.8225005, "way_id": 233604538, "landuse": "farmland", "closest_distance_restriction": 2.7491406531770797}, {"id": 7726919305, "lat": 49.6518829, "lon": 21.8215727, "way_id": 233604538, "landuse": "farmland", "closest_distance_restriction": 2.705307122448878}, {"id": 7726919321, "lat": 49.6532327, "lon": 21.8243193, "way_id": 233604538, "landuse": "farmland", "closest_distance_restriction": 2.8398564087125084}, {"id": 7726919341, "lat": 49.655177, "lon": 21.8280067, "way_id": 233604538, "landuse": "farmland", "closest_distance_restriction": 2.8852375098283143}]}