{"nodes": [{"id": 682236441, "lat": 53.8209937, "lon": 20.4179701, "way_id": 545566142, "landuse": "farmland", "closest_distance_restriction": 1.6443589875331068}, {"id": 5272719665, "lat": 53.8202782, "lon": 20.4179452, "way_id": 545566142, "landuse": "farmland", "closest_distance_restriction": 1.5778295456034894}, {"id": 5272719666, "lat": 53.8200422, "lon": 20.4186992, "way_id": 545566142, "landuse": "farmland", "closest_distance_restriction": 1.5859254020955778}, {"id": 5272719667, "lat": 53.8203425, "lon": 20.4189627, "way_id": 545566142, "landuse": "farmland", "closest_distance_restriction": 1.6221075038748114}, {"id": 5272719668, "lat": 53.820667, "lon": 20.4177786, "way_id": 545566142, "landuse": "farmland", "closest_distance_restriction": 1.6071883446957427}, {"id": 5272719669, "lat": 53.8210611, "lon": 20.4181451, "way_id": 545566142, "landuse": "farmland", "closest_distance_restriction": 1.6569748404156484}, {"id": 5272719670, "lat": 53.8207662, "lon": 20.4192716, "way_id": 545566142, "landuse": "farmland", "closest_distance_restriction": 1.635566054597533}, {"id": 5272719671, "lat": 53.8221283, "lon": 20.4203163, "way_id": 545566142, "landuse": "farmland", "closest_distance_restriction": 1.686284874282479}, {"id": 5272719672, "lat": 53.8216457, "lon": 20.422006, "way_id": 545566142, "landuse": "farmland", "closest_distance_restriction": 1.57031093504961}]}